SRA_Importer/__init__.py
SRA_Importer/create_visualization.py
SRA_Importer/export_data.py
SRA_Importer/utilities.py
SRA_Importer-0.0.11.dist-info/METADATA
SRA_Importer-0.0.11.dist-info/WHEEL
SRA_Importer-0.0.11.dist-info/top_level.txt
SRA_Importer-0.0.11.dist-info/RECORD
