Metadata-Version: 2.1
Name: SRA-Importer
Version: 0.0.11
Summary: An easy and convenient way to import data from the sra database and creating OTU and Taxonomy tables.
Home-page: https://github.com/AmitKabya/SRA-Importer
Author: Amit Kabya
Maintainer: Amit Kabya
Maintainer-email: kabya.amit@gmail.com
License: MIT
Keywords: sra,bioinformatics,qiime2,taxonomy
Classifier: Programming Language :: Python
Classifier: License :: OSI Approved :: MIT License
Requires-Python: >=3.6.8
Requires-Dist: setuptools
